Tigger/Coordinates.py
Tigger/Models/Formats/AIPSCC.py
Tigger/Models/Formats/AIPSCCFITS.py
Tigger/Models/Formats/ASCII.py
Tigger/Models/Formats/BBS.py
Tigger/Models/Formats/ModelHTML.py
Tigger/Models/Formats/NEWSTAR.py
Tigger/Models/Formats/PyBDSMGaul.py
Tigger/Models/Formats/__init__.py
Tigger/Models/Formats/ds9.py
Tigger/Models/ModelClasses.py
Tigger/Models/PlotStyles.py
Tigger/Models/SkyModel.py
Tigger/Models/__init__.py
Tigger/SiameseInterface.py
Tigger/Tools/FITSHeaders.py
Tigger/Tools/Imaging.py
Tigger/Tools/__init__.py
Tigger/Tools/gaussfitter2.py
Tigger/__init__.py
Tigger/bin/__init__.py
Tigger/bin/tigger_convert.py
Tigger/bin/tigger_make_brick.py
Tigger/bin/tigger_restore.py
Tigger/bin/tigger_tag.py
Tigger/version_info/__init__.py
astro_tigger_lsm-1.8.0.dist-info/METADATA
astro_tigger_lsm-1.8.0.dist-info/WHEEL
astro_tigger_lsm-1.8.0.dist-info/entry_points.txt
astro_tigger_lsm-1.8.0.dist-info/RECORD
