Metadata-Version: 2.1
Name: astro-tigger-lsm
Version: 1.8.0
Summary: Python libraries and command-line tools for manipulating Tigger LSMs
Author: Oleg Smirnov
Author-email: osmirnov@gmail.com
Requires-Python: >=3.9,<4.0
Classifier: Programming Language :: Python :: 3
Classifier: Programming Language :: Python :: 3.9
Classifier: Programming Language :: Python :: 3.10
Classifier: Programming Language :: Python :: 3.11
Classifier: Programming Language :: Python :: 3.12
Requires-Dist: astro-kittens (>=1.4.6,<2.0.0)
Requires-Dist: astropy (>=5)
Requires-Dist: future
Requires-Dist: meqtrees-cattery (>=1.7.9,<2.0.0)
Requires-Dist: numpy
Requires-Dist: python-casacore
Requires-Dist: scipy
